runtypes/__init__.py
runtypes/hints.py
runtypes/py.typed
runtypes/runtype.py
runtypes/tuples.py
runtypes/types/__init__.py
runtypes/types/advanced.py
runtypes/types/basic.py
runtypes-0.6.3.dist-info/LICENSE
runtypes-0.6.3.dist-info/METADATA
runtypes-0.6.3.dist-info/WHEEL
runtypes-0.6.3.dist-info/top_level.txt
runtypes-0.6.3.dist-info/RECORD
