Metadata-Version: 2.1
Name: runtypes
Version: 0.6.3
Summary: A simple library for runtime validation of types.
Maintainer-email: Nadav Tasher <hey@nadav.app>
License: MIT License
Project-URL: Homepage, https://github.com/NadavTasher/RunTypes
Keywords: runtime,typing,typecheck
Classifier: License :: OSI Approved :: MIT License
Classifier: Programming Language :: Python
Classifier: Programming Language :: Python :: 3
Requires-Python: >=3.8
License-File: LICENSE
